gotime/__init__.py
gotime/cli.py
gotime/gotime.py
gotime/maps.py
gotime-0.1.4.dist-info/AUTHORS.rst
gotime-0.1.4.dist-info/LICENSE
gotime-0.1.4.dist-info/METADATA
gotime-0.1.4.dist-info/WHEEL
gotime-0.1.4.dist-info/entry_points.txt
gotime-0.1.4.dist-info/top_level.txt
gotime-0.1.4.dist-info/RECORD
