Metadata-Version: 2.1
Name: gotime
Version: 0.1.4
Summary: How long does it take to get from Point A to Point B
Home-page: https://github.com/mgeiger/gotime
Author: Matthew J. Geiger
Author-email: matthew.j.geiger@gmail.com
License: MIT license
Keywords: gotime
Platform: UNKNOWN
Classifier: Development Status :: 2 - Pre-Alpha
Classifier: Intended Audience :: Developers
Classifier: License :: OSI Approved :: MIT License
Classifier: Natural Language :: English
Classifier: Programming Language :: Python :: 3
Classifier: Programming Language :: Python :: 3.6
Classifier: Programming Language :: Python :: 3.7
Classifier: Programming Language :: Python :: 3.8
Requires-Dist: Click (>=6.0)
